<?xml version="1.0" encoding="utf-8"?> 
<TEXT>
<SENTENSE Ver="1" Id="ABOUT_BOX_ID_OK">
<VALUE Lang="Common">OK</VALUE>
</SENTENSE>
<SENTENSE Ver="1" Id="DISCOURAGES">
<VALUE Lang="Common">Not Recommended</VALUE>
</SENTENSE>
<SENTENSE Ver="1" Id="DISCOURAGES_MESSAGE">
<VALUE Lang="Common">The best resolution for this game is 1024 X 768, but the display mode that your choose is non-recommended.</VALUE>
</SENTENSE>
<SENTENSE Ver="1" Id="DOWNAREA_ID_OK">
<VALUE Lang="Common">OK</VALUE>
</SENTENSE>
<SENTENSE Ver="1" Id="GAMESET_ID_CANCEL">
<VALUE Lang="Common">Cancel</VALUE>
</SENTENSE>
<SENTENSE Ver="1" Id="GAMESET_ID_OK">
<VALUE Lang="Common">Save</VALUE>
</SENTENSE>
<SENTENSE Ver="1" Id="IDC_AREA_STATIC">
<VALUE Lang="Common">Not String</VALUE>
</SENTENSE>
<SENTENSE Ver="1" Id="IDC_ATI_STATIC">
<VALUE Lang="Common">ATI  ( Radeon )</VALUE>
</SENTENSE>
<SENTENSE Ver="1" Id="IDC_BUTTON_EXIT">
<VALUE Lang="Common">Exit</VALUE>
</SENTENSE>
<SENTENSE Ver="1" Id="IDC_BUTTON_OPTION">
<VALUE Lang="Common">Option</VALUE>
</SENTENSE>
<SENTENSE Ver="1" Id="IDC_BUTTON_PATCH">
<VALUE Lang="Common">Action</VALUE>
</SENTENSE>
<SENTENSE Ver="1" Id="IDC_BUTTON_RETRY">
<VALUE Lang="Common">Not String</VALUE>
</SENTENSE>
<SENTENSE Ver="1" Id="IDC_BUTTON_START">
<VALUE Lang="Common">Start</VALUE>
</SENTENSE>
<SENTENSE Ver="1" Id="IDC_CHECK_NOCHECK">
<VALUE Lang="Common">Don't caution next time.</VALUE>
</SENTENSE>
<SENTENSE Ver="1" Id="IDC_CHECK_PASSIVE">
<VALUE Lang="Common">Passive Mode</VALUE>
</SENTENSE>
<SENTENSE Ver="1" Id="IDC_CHECK_USE_HTTP">
<VALUE Lang="Common">http</VALUE>
</SENTENSE>
<SENTENSE Ver="1" Id="IDC_CHECK_WINDOWMODE">
<VALUE Lang="Common">window mode</VALUE>
</SENTENSE>
<SENTENSE Ver="1" Id="IDC_DISPLAY_STATIC">
<VALUE Lang="Common">Display</VALUE>
</SENTENSE>
<SENTENSE Ver="1" Id="IDC_DOWNAREA_STATIC">
<VALUE Lang="Common">DownLoad Area</VALUE>
</SENTENSE>
<SENTENSE Ver="1" Id="IDC_DOWNLOAD_STATIC">
<VALUE Lang="Common">Download</VALUE>
</SENTENSE>
<SENTENSE Ver="1" Id="IDC_NVIDIA_STATIC">
<VALUE Lang="Common">nVidia  ( Geforce, TNT )</VALUE>
</SENTENSE>
<SENTENSE Ver="1" Id="IDC_READYTOSTART">
<VALUE Lang="Common">When the game is prepared, start</VALUE>
</SENTENSE>
<SENTENSE Ver="1" Id="IDC_STATIC_ATI_LINK">
<VALUE Lang="Common">Driver Download</VALUE>
</SENTENSE>
<SENTENSE Ver="1" Id="IDC_STATIC_DOWNLOAD">
<VALUE Lang="Common">Download</VALUE>
</SENTENSE>
<SENTENSE Ver="1" Id="IDC_STATIC_DOWNLOAD2">
<VALUE Lang="Common">Overall progress</VALUE>
</SENTENSE>
<SENTENSE Ver="1" Id="IDC_STATIC_HOMEPAGE">
<VALUE Lang="Common">Homepage</VALUE>
</SENTENSE>
<SENTENSE Ver="1" Id="IDC_STATIC_NVIDIA_LINK">
<VALUE Lang="Common">Driver Download</VALUE>
</SENTENSE>
<SENTENSE Ver="1" Id="IDC_TITLE_STATIC">
<VALUE Lang="Common">RAN-Online</VALUE>
</SENTENSE>
<SENTENSE Ver="1" Id="IDC_VER_STATIC">
<VALUE Lang="Common">AutoPatchMan Version 1.0</VALUE>
<VALUE Lang="Common">Copyright (c) 2002</VALUE>
</SENTENSE>
<SENTENSE Ver="1" Id="IDC_VIDEO_STATIC">
<VALUE Lang="Common">Windows Hardware Quality Labs (WHQL) Certified</VALUE>
<VALUE Lang="Common">Video Driver is not installed.</VALUE>
<VALUE Lang="Common">if Windows Hardware Quality Labs (WHQL) Certified Video Driver is not installed,</VALUE>
<VALUE Lang="Common">it's possible to make error while playing game.</VALUE>
</SENTENSE>
<SENTENSE Ver="1" Id="IDD_ABOUT_BOX">
<VALUE Lang="Common">AutoPatchMan Information</VALUE>
</SENTENSE>
<SENTENSE Ver="1" Id="IDD_DIALOG_DOWNLOAD_AREA">
<VALUE Lang="Common">DOWNLOAD AREA</VALUE>
</SENTENSE>
<SENTENSE Ver="1" Id="IDD_DIALOG_WARNING_WHQL">
<VALUE Lang="Common">Caution</VALUE>
</SENTENSE>
<SENTENSE Ver="1" Id="IDD_GAMESETDLG">
<VALUE Lang="Common">Option</VALUE>
</SENTENSE>
<SENTENSE Ver="1" Id="WARNING_ID_OK">
<VALUE Lang="Common">OK</VALUE>
</SENTENSE>
<WORD Ver="1" Id="IDC_GRAPHIC_OPTION">
<VALUE Lang="Common" Index="0">Graphic</VALUE>
<VALUE Lang="Common" Index="1">Default Option</VALUE>
<VALUE Lang="Common" Index="2">View</VALUE>
<VALUE Lang="Common" Index="3">Character Shadow</VALUE>
<VALUE Lang="Common" Index="4">Character Detail</VALUE>
<VALUE Lang="Common" Index="5">Field Shadow</VALUE>
<VALUE Lang="Common" Index="6">Realtime Reflection</VALUE>
<VALUE Lang="Common" Index="7">Scene Distortion</VALUE>
<VALUE Lang="Common" Index="8">Glow Effect</VALUE>
<VALUE Lang="Common" Index="9">Buff Effect</VALUE>
<VALUE Lang="Common" Index="10">POST PROCESSING</VALUE>
<VALUE Lang="Common" Index="11">Game Cursor</VALUE>
<VALUE Lang="Common" Index="12">Texture Font</VALUE>
<VALUE Lang="Common" Index="13">Used limit Frame</VALUE>
<VALUE Lang="Common" Index="14">Please select opponent effect</VALUE>
<VALUE Lang="Common" Index="15">Item effect showed</VALUE>
<VALUE Lang="Common" Index="16">Map point function</VALUE>
<VALUE Lang="Common" Index="17">Using Normal Map</VALUE>
</WORD>
<WORD Ver="1" Id="IDC_SOUND_OPTION">
<VALUE Lang="Common" Index="0">Sound</VALUE>
<VALUE Lang="Common" Index="1">3D Sound</VALUE>
<VALUE Lang="Common" Index="2">Find</VALUE>
<VALUE Lang="Common" Index="3">BGM</VALUE>
<VALUE Lang="Common" Index="4">MAP</VALUE>
<VALUE Lang="Common" Index="5">SFX</VALUE>
</WORD>
<WORD Ver="1" Id="IDS_ABOUTBOX">
<VALUE Lang="Common" Index="0">AutoPatchMan Info.(&amp;A)...</VALUE>
</WORD>
<WORD Ver="1" Id="IDS_MESSAGE">
<VALUE Lang="Common" Index="0">Ran Online</VALUE>
<VALUE Lang="Common" Index="1">Run on the Web environment.</VALUE>
<VALUE Lang="Common" Index="2">Ran-Online file is damaged. Please reinstall Ran-Online.</VALUE>
<VALUE Lang="Common" Index="3">Closing. wait a moment.</VALUE>
<VALUE Lang="Common" Index="4">Program restart  failed after patch.</VALUE>
<VALUE Lang="Common" Index="5">Winsock version is not suitable.</VALUE>
<VALUE Lang="Common" Index="6">DirextX version is not suitable.</VALUE>
<VALUE Lang="Common" Index="7">Please play after updating DirectX.</VALUE>
<VALUE Lang="Common" Index="8">Server is now inspected. Please conect a little bit later.</VALUE>
<VALUE Lang="Common" Index="9">Version file reading  failed.</VALUE>
<VALUE Lang="Common" Index="10">Error occurs while program patch file loading.</VALUE>
<VALUE Lang="Common" Index="11">Error occurs whlile program patch file installing.</VALUE>
<VALUE Lang="Common" Index="12">Finished prepare to game play.</VALUE>
<VALUE Lang="Common" Index="13">Connecting Server failed. reach the max try connecting.</VALUE>
<VALUE Lang="Common" Index="14">Trying to connection......</VALUE>
<VALUE Lang="Common" Index="15">Connecting Server failed. over the max connection time.</VALUE>
<VALUE Lang="Common" Index="16">Connecting Server OK, data transmission succeed.</VALUE>
<VALUE Lang="Common" Index="17">Try to connection FTP......</VALUE>
<VALUE Lang="Common" Index="18">Connecting FTP Server fails due to over connection time.</VALUE>
<VALUE Lang="Common" Index="19">Connect to FTP Server,  data transmission success.</VALUE>
<VALUE Lang="Common" Index="20">Creating event fails.</VALUE>
<VALUE Lang="Common" Index="21">Selecting event fails.</VALUE>
<VALUE Lang="Common" Index="22">Connecting fails.</VALUE>
<VALUE Lang="Common" Index="23">Waiting for event fails.</VALUE>
<VALUE Lang="Common" Index="24">Contact event was not occured.</VALUE>
<VALUE Lang="Common" Index="25">Thread Creating fails.</VALUE>
<VALUE Lang="Common" Index="26">Unable to connect to Server.</VALUE>
<VALUE Lang="Common" Index="27">Version data transmission failed.</VALUE>
<VALUE Lang="Common" Index="28">Forced termination accomplished.</VALUE>
<VALUE Lang="Common" Index="29">Can't find file to start launch program.</VALUE>
<VALUE Lang="Common" Index="30">Sound card is missing or out of order.</VALUE>
<VALUE Lang="Common" Index="31">None</VALUE>
<VALUE Lang="Common" Index="32">Low</VALUE>
<VALUE Lang="Common" Index="33">Middle</VALUE>
<VALUE Lang="Common" Index="34">High</VALUE>
<VALUE Lang="Common" Index="35">Higher</VALUE>
<VALUE Lang="Common" Index="36">Low</VALUE>
<VALUE Lang="Common" Index="37">Middle</VALUE>
<VALUE Lang="Common" Index="38">High</VALUE>
<VALUE Lang="Common" Index="39">Standard</VALUE>
<VALUE Lang="Common" Index="40">Hardware Acceleration HALF</VALUE>
<VALUE Lang="Common" Index="41">Hardware Acceleration FULL</VALUE>
<VALUE Lang="Common" Index="42">Near</VALUE>
<VALUE Lang="Common" Index="43">Far</VALUE>
<VALUE Lang="Common" Index="44">Further</VALUE>
<VALUE Lang="Common" Index="45">Connecting FTP Server fails.</VALUE>
<VALUE Lang="Common" Index="46">Size of downloaded file is wrong.</VALUE>
<VALUE Lang="Common" Index="47">Patch file is being transmitted......</VALUE>
<VALUE Lang="Common" Index="48">Patching......</VALUE>
<VALUE Lang="Common" Index="49">Patch list file is being transmitted.</VALUE>
<VALUE Lang="Common" Index="50">Error occurs while patch list file transmitting.</VALUE>
<VALUE Lang="Common" Index="51">Decompressing patch list file.</VALUE>
<VALUE Lang="Common" Index="52">Decompressing patch list file fails.</VALUE>
<VALUE Lang="Common" Index="53">Loading patch file list.</VALUE>
<VALUE Lang="Common" Index="54">Loading patch file list fails.</VALUE>
<VALUE Lang="Common" Index="55">Error occurs while patch file transmitting.</VALUE>
<VALUE Lang="Common" Index="56">Please check 'passive mode' on 'option' menu, 'download' tap,</VALUE>
<VALUE Lang="Common" Index="57">Comparing patch file list.</VALUE>
<VALUE Lang="Common" Index="58">Comparing patch file list fails.</VALUE>
<VALUE Lang="Common" Index="59">A part of patch file is damaged.</VALUE>
<VALUE Lang="Common" Index="60">Renewing client version.</VALUE>
<VALUE Lang="Common" Index="61">Renewing client version fails.</VALUE>
<VALUE Lang="Common" Index="62">It accomplished all patch work successfully.</VALUE>
<VALUE Lang="Common" Index="63">and try again.</VALUE>
<VALUE Lang="Common" Index="64">Please try again after changing the downlaoding server from Option.</VALUE>
<VALUE Lang="Common" Index="65">Initiating the file comparisons...</VALUE>
<VALUE Lang="Common" Index="66">Completed the file comparisons!</VALUE>
<VALUE Lang="Common" Index="67">Creating the list needed for the file comparisons...</VALUE>
<VALUE Lang="Common" Index="68">Failed to create the file comparisons list! </VALUE>
<VALUE Lang="Common" Index="69">Comparing the files...</VALUE>
<VALUE Lang="Common" Index="70">Zipping down the file...</VALUE>
<VALUE Lang="Common" Index="71">Failed to zip down the file!</VALUE>
<VALUE Lang="Common" Index="72">Failed to execute the optimization!</VALUE>
<VALUE Lang="Common" Index="73">User definitions</VALUE>
<VALUE Lang="Common" Index="74">Extract the files failed.</VALUE>
<VALUE Lang="Common" Index="75">Has failed to specify the compressed folder.</VALUE>
<VALUE Lang="Common" Index="76">Failed to delete file.</VALUE>
<VALUE Lang="Common" Index="77">Need to prepare for the game has not been completed</VALUE>
<VALUE Lang="Common" Index="78">Please click the "UPDATE START" button to download</VALUE>
</WORD>
<WORD Ver="1" Id="IDS_WHQL_CVD">
<VALUE Lang="Common" Index="0">WHQL Certified Video Driver</VALUE>
</WORD>
<WORD Ver="1" Id="IDS_WHQL_UCVD">
<VALUE Lang="Common" Index="0">WHQL Uncertified Video Driver</VALUE>
</WORD>
</TEXT>